autokernel/__init__.py
autokernel/autokernel.py
autokernel/config.py
autokernel/kconfig.py
autokernel/lkddb.py
autokernel/log.py
autokernel/node_detector.py
autokernel/subsystem.py
autokernel/symbol_tracking.py
autokernel/util.py
autokernel/contrib/__init__.py
autokernel/contrib/config.lark
autokernel/contrib/internal.conf
autokernel/contrib/etc/__init__.py
autokernel/contrib/etc/autokernel.conf
autokernel/contrib/etc/modules_d/__init__.py
autokernel/contrib/etc/modules_d/acpi.conf
autokernel/contrib/etc/modules_d/audio.conf
autokernel/contrib/etc/modules_d/block.conf
autokernel/contrib/etc/modules_d/bluetooth.conf
autokernel/contrib/etc/modules_d/console.conf
autokernel/contrib/etc/modules_d/crypto.conf
autokernel/contrib/etc/modules_d/filesystems.conf
autokernel/contrib/etc/modules_d/hardening.conf
autokernel/contrib/etc/modules_d/local.conf
autokernel/contrib/etc/modules_d/local_detected.conf
autokernel/contrib/etc/modules_d/misc.conf
autokernel/contrib/etc/modules_d/net.conf
autokernel/contrib/etc/modules_d/pci.conf
autokernel/contrib/etc/modules_d/raid.conf
autokernel/contrib/etc/modules_d/systemd.conf
autokernel/contrib/etc/modules_d/usb.conf
autokernel/contrib/etc/modules_d/virt.conf
autokernel/contrib/example_configs/laptop_autokernel.conf
autokernel-0.9.9.dist-info/AUTHORS
autokernel-0.9.9.dist-info/LICENSE
autokernel-0.9.9.dist-info/METADATA
autokernel-0.9.9.dist-info/WHEEL
autokernel-0.9.9.dist-info/entry_points.txt
autokernel-0.9.9.dist-info/pbr.json
autokernel-0.9.9.dist-info/top_level.txt
autokernel-0.9.9.dist-info/zip-safe
autokernel-0.9.9.dist-info/RECORD
