Metadata-Version: 2.1
Name: autokernel
Version: 0.9.9
Summary: A tool to autodetect and manage kernel configuration options
Home-page: https://github.com/oddlama/autokernel
Author: oddlama
Author-email: oddlama@oddlama.org
Maintainer: oddlama
Maintainer-email: oddlama@oddlama.org
License: MIT
Keywords: autokernel,config,detect,detection,kconf,kconfiglib,kernel,manager
Platform: UNKNOWN
Classifier: Development Status :: 4 - Beta
Classifier: Environment :: Console
Classifier: Intended Audience :: End Users/Desktop
Classifier: Intended Audience :: System Administrators
Classifier: Intended Audience :: Information Technology
Classifier: License :: OSI Approved :: MIT License
Classifier: Operating System :: POSIX :: Linux
Classifier: Programming Language :: Python :: 3 :: Only
Classifier: Programming Language :: Python :: 3.6
Classifier: Topic :: Security
Classifier: Topic :: System :: Operating System Kernels
Classifier: Topic :: System :: Operating System Kernels :: Linux
Classifier: Topic :: Utilities
Requires-Python: >=3.6
Requires-Dist: kconfiglib
Requires-Dist: lark-parser
Requires-Dist: python-dateutil
Requires-Dist: requests
Requires-Dist: sympy
Requires-Dist: importlib-resources ; (python_version<'3.7')
